src/def.v
//Instruction codification

`define LDA   	6'h00
`define LDB   	6'h01
`define LDCA   	6'h02
`define LDCB   	6'h03
`define STA   	6'h04
`define STA   	6'h05

`define ADDA   	6'h06
`define ADDB   	6'h07
`define ADDCA  	6'h08
`define ADDCB  	6'h09
`define SUBA   	6'h0A
`define SUBB   	6'h0B
`define SUBCA  	6'h0C
`define SUBCB  	6'h0D

`define ANDA   	6'h0E
`define ANDB   	6'h0F
`define ANDCA  	6'h10
`define ANDCB  	6'h11
`define ORA   	6'h12
`define ORB   	6'h13
`define ORCA  	6'h14
`define ORCB  	6'h15

`define ASLA   	6'h16
`define ASRA   	6'h17

`define JMP   	6'h18

`define BAEQ   	6'h19
`define BANE   	6'h1A
`define BACS   	6'h1B
`define BACC   	6'h1C
`define BAMI   	6'h1D
`define BAPL   	6'h1E

`define BBEQ   	6'h1F
`define BBNE   	6'h20
`define BBCS   	6'h21
`define BBCC   	6'h22
`define BBMI   	6'h23
`define BBPL   	6'h24

`define NOP   	6'h25

src/alu.v
`include "def.v"
`include "aux.v"

module alu
(
	//Entradas de control
	input wire 		clk,
	input wire		reset,
	input wire [5:0]	opcode,

	//Entradas de datos
	input wire [7:0] 	in1,
	input wire [7:0]	in2,

	//Salidas
	output reg [7:0]  	out
);


always @ ( posedge clk )
begin
	case (opcode)
	//Oparaciones de transferencia de datos
	`LDA:
	begin
		out	<= 	8'b0;			
	end
	`LDB:
	begin
		out	<= 	8'b0;			
	end

	`LDCA:
	begin
		out	<= 	8'b0;			
	end
	`LDCB:
	begin
		out	<= 	8'b0;			
	end


	`STA:
	begin
		out	<= 	in1;		
	end

	`STB:
	begin
		out	<= 	in2;		
	end
	//-------------------------------------

	//Oparaciones aritmeticas
	`ADDA:
	begin
		out	<= 	in1 + in2;	
	end
	`ADDB:
	begin
		out	<= 	in1 + in2;
	end

	`ADDCA:
	begin
		out	<= 	in1 + in2;	
	end
	`ADDCB:
	begin
		out	<= 	in1 + in2;
	end

	`SUBA:
	begin
		out	<= 	in1 - in2;	
	end
	`SUBB:
	begin
		out	<= 	in2 - in1;
	end

	`SUBCA:
	begin
		out	<= 	in1 - in2;	
	end
	`SUBCB:
	begin
		out	<= 	in2 - in1;
	end
	//-------------------------------------

	//Oparaciones logicas

	`ANDA:
	begin
		out	<= 	in1 & in2;	
	end
	`ANDB:
	begin
		out	<= 	in2 & in1;
	end

	`ANDCA:
	begin
		out	<= 	in1 & in2;	
	end
	`ANDCB:
	begin
		out	<= 	in2 & in1;
	end

	`ORA:
	begin
		out	<= 	in1 | in2;	
	end
	`ORB:
	begin
		out	<= 	in2 | in1;
	end

	`ORCA:
	begin
		out	<= 	in1 | in2;	
	end
	`ORCB:
	begin
		out	<= 	in2 | in1;
	end

	`ASLA:
	begin
		out	<= 	in1 << 1;	
	end
	`ASRA:
	begin
		out	<= 	in1 >> 1;
	end

	//-------------------------------------

	//Oparaciones de control de flujo
		//Ninguna de las operaciones de control de flujo requiere la ALU,
		//estas operaciones ejecutan el default.
	//-------------------------------------

	//Otras
	`NOP:
	begin
		out	<= 	8'b0;			
	end
	//-------------------------------------
	default:
	begin
		out	<= 	8'b0;	
	end	
	endcase	
end
endmodule

src/testbench.v
`timescale 1ns / 1ps
`include "alu.v"
`include "def.v"

module testbench;

//Inputs

reg [7:0] wIn1;
reg [7:0] wIn2;

reg [5:0] wOp;

//Outputs
wire [7:0] wAlu;


reg Clock;
reg Reset;

always 
begin
	#5 Clock = ! Clock;
end

alu a0 
(
	.clk(Clock),
	.reset(Reset),
	.opcode(wOp),
	.in1(wIn1),
	.in2(wIn2),
	.out(wAlu)
);


initial 
begin
	Clock = 0;
	#05 	Reset=1; #05 Reset=0;

	#5	wOp = `ADDA; 	wIn1 = 8'd21; 	wIn2 = 8'd5;
	#10 	wOp = `ADDB; 	wIn1 = 8'd21; 	wIn2 = 8'd4;
	#10 	wOp = `ADDCA; 	wIn1 = 8'd21; 	wIn2 = 8'd5;	
	#10	wOp = `ADDCB; 	wIn1 = 8'd21; 	wIn2 = 8'd4;

	#10	wOp = `SUBA; 	wIn1 = 8'd21; 	wIn2 = 8'd5;
	#10 	wOp = `SUBB; 	wIn1 = 8'd21; 	wIn2 = 8'd4;
	#10 	wOp = `SUBCA; 	wIn1 = 8'd21; 	wIn2 = 8'd5;	
	#10	wOp = `SUBCB; 	wIn1 = 8'd21; 	wIn2 = 8'd4;

	#10	wOp = `ANDA; 	wIn1 = 8'd13; 	wIn2 = 8'd5;
	#10 	wOp = `ANDB; 	wIn1 = 8'd13; 	wIn2 = 8'd4;
	#10 	wOp = `ANDCA; 	wIn1 = 8'd13; 	wIn2 = 8'd5;	
	#10	wOp = `ANDCB; 	wIn1 = 8'd13; 	wIn2 = 8'd4;

	#10	wOp = `ORA; 	wIn1 = 8'd13; 	wIn2 = 8'd5;
	#10 	wOp = `ORB; 	wIn1 = 8'd13; 	wIn2 = 8'd4;
	#10 	wOp = `ORCA; 	wIn1 = 8'd13; 	wIn2 = 8'd5;	
	#10	wOp = `ORCB; 	wIn1 = 8'd13; 	wIn2 = 8'd4;

	#10 	wOp = `ASLA; 	wIn1 = 8'd4; 	wIn2 = 8'd5;	
	#10	wOp = `ASRA; 	wIn1 = 8'd4; 	wIn2 = 8'd5;

	#10
	$finish;
end

initial 
begin
	$dumpfile("sim1.vcd");
	$dumpvars;
end


endmodule

src/aux.v
/*--Auxiliary Modules-----------------------------//
Modules:
		1)UPCOUNTER_POSEDGE
		2)FFD_POSEDGE
		3)FULL_ADDER
		4)RAM

//------------------------------------------------*/

module UPCOUNTER_POSEDGE # (parameter SIZE=16)
(
input wire Clock, Reset,
input wire [SIZE-1:0] Initial,
input wire Enable,
output reg [SIZE-1:0] Q
);

  always @(posedge Clock )
  begin
      if (Reset)
        Q = Initial;
      else
		begin
		if (Enable)
			Q = Q + 1;
			
		end			
  end

endmodule

//------------------------------------------------//

module FFD_POSEDGE_SYNCRONOUS_RESET # ( parameter SIZE=8 )
(
	input wire				Clock,
	input wire				Reset,
	input wire				Enable,
	input wire [SIZE-1:0]	D,
	output reg [SIZE-1:0]	Q
);
	
always @ (posedge Clock) 
begin
	if ( Reset )
		Q <= 0;
	else
	begin	
		if (Enable) 
			Q <= D; 
	end	
 
end
endmodule

//------------------------------------------------//

module FULL_ADDER # (parameter SIZE=8) 
(
	input  wire [SIZE-1:0] 	In1,
	input  wire [SIZE-1:0] 	In2,
	input  wire		Ci,
	output wire [SIZE-1:0] 	Out,
	output wire [SIZE-1:0]	Co
);

assign {Co,Out} = In1 + In2 + Ci;
endmodule

//------------------------------------------------//

module RAM_SINGLE_READ_PORT # ( parameter DATA_WIDTH= 8, parameter ADDR_WIDTH=10, parameter MEM_SIZE=10 )
(
	input wire			Clock,
	input wire			iWriteEnable,
	input wire[ADDR_WIDTH-1:0]	iReadAddress,
	input wire[ADDR_WIDTH-1:0]	iWriteAddress,
	input wire[DATA_WIDTH-1:0]	iDataIn,
	output reg [DATA_WIDTH-1:0] 	oDataOut
);

reg [DATA_WIDTH-1:0] Ram [MEM_SIZE:0];		

always @(posedge Clock) 
begin 
	
		if (iWriteEnable) 
			Ram[iWriteAddress] <= iDataIn; 
			
		oDataOut <=(( iWriteAddress == iReadAddress ) && iWriteEnable ) ? iDataIn : Ram[iReadAddress ] ;
end 
endmodule

//------------------------------------------------//

src/sim1.vcd
$date
	Wed Jun  3 09:59:30 2015
$end
$version
	Icarus Verilog
$end
$timescale
	1ps
$end
$scope module FFD_POSEDGE_SYNCRONOUS_RESET $end
$var wire 1 ! Clock $end
$var wire 8 " D [7:0] $end
$var wire 1 # Enable $end
$var wire 1 $ Reset $end
$var reg 8 % Q [7:0] $end
$upscope $end
$scope module FULL_ADDER $end
$var wire 1 & Ci $end
$var wire 8 ' Co [7:0] $end
$var wire 8 ( In1 [7:0] $end
$var wire 8 ) In2 [7:0] $end
$var wire 8 * Out [7:0] $end
$upscope $end
$scope module RAM_SINGLE_READ_PORT $end
$var wire 1 + Clock $end
$var wire 8 , iDataIn [7:0] $end
$var wire 10 - iReadAddress [9:0] $end
$var wire 10 . iWriteAddress [9:0] $end
$var wire 1 / iWriteEnable $end
$var reg 8 0 oDataOut [7:0] $end
$upscope $end
$scope module UPCOUNTER_POSEDGE $end
$var wire 1 1 Clock $end
$var wire 1 2 Enable $end
$var wire 16 3 Initial [15:0] $end
$var wire 1 4 Reset $end
$var reg 16 5 Q [15:0] $end
$upscope $end
$scope module testbench $end
$var wire 8 6 wAlu [7:0] $end
$var reg 1 7 Clock $end
$var reg 1 8 Reset $end
$var reg 8 9 wIn1 [7:0] $end
$var reg 8 : wIn2 [7:0] $end
$var reg 6 ; wOp [5:0] $end
$scope module a0 $end
$var wire 1 < clk $end
$var wire 8 = in1 [7:0] $end
$var wire 8 > in2 [7:0] $end
$var wire 6 ? opcode [5:0] $end
$var wire 1 @ reset $end
$var reg 8 A out [7:0] $end
$upscope $end
$upscope $end
$enddefinitions $end
#0
$dumpvars
bx A
x@
bx ?
bx >
bx =
0<
bx ;
bx :
bx 9
x8
07
bx 6
bx 5
z4
bz 3
z2
z1
bx 0
z/
bz .
bz -
bz ,
z+
bx *
bz )
bz (
bx '
z&
bx %
z$
z#
bz "
z!
$end
#5000
b0 A
b0 6
18
1@
17
1<
#10000
08
0@
07
0<
#15000
b11010 A
b11010 6
b101 :
b101 >
b10101 9
b10101 =
b110 ;
b110 ?
17
1<
#20000
07
0<
#25000
b11001 A
b11001 6
17
1<
b100 :
b100 >
b111 ;
b111 ?
#30000
07
0<
#35000
b11010 A
b11010 6
17
1<
b101 :
b101 >
b1000 ;
b1000 ?
#40000
07
0<
#45000
b11001 A
b11001 6
17
1<
b100 :
b100 >
b1001 ;
b1001 ?
#50000
07
0<
#55000
b10000 A
b10000 6
17
1<
b101 :
b101 >
b1010 ;
b1010 ?
#60000
07
0<
#65000
b11101111 A
b11101111 6
17
1<
b100 :
b100 >
b1011 ;
b1011 ?
#70000
07
0<
#75000
b10000 A
b10000 6
17
1<
b101 :
b101 >
b1100 ;
b1100 ?
#80000
07
0<
#85000
b11101111 A
b11101111 6
17
1<
b100 :
b100 >
b1101 ;
b1101 ?
#90000
07
0<
#95000
b101 A
b101 6
17
1<
b101 :
b101 >
b1101 9
b1101 =
b1110 ;
b1110 ?
#100000
07
0<
#105000
b100 A
b100 6
17
1<
b100 :
b100 >
b1111 ;
b1111 ?
#110000
07
0<
#115000
b101 A
b101 6
17
1<
b101 :
b101 >
b10000 ;
b10000 ?
#120000
07
0<
#125000
b100 A
b100 6
17
1<
b100 :
b100 >
b10001 ;
b10001 ?
#130000
07
0<
#135000
b1101 A
b1101 6
17
1<
b101 :
b101 >
b10010 ;
b10010 ?
#140000
07
0<
#145000
17
1<
b100 :
b100 >
b10011 ;
b10011 ?
#150000
07
0<
#155000
17
1<
b101 :
b101 >
b10100 ;
b10100 ?
#160000
07
0<
#165000
17
1<
b100 :
b100 >
b10101 ;
b10101 ?
#170000
07
0<
#175000
b1000 A
b1000 6
17
1<
b101 :
b101 >
b100 9
b100 =
b10110 ;
b10110 ?
#180000
07
0<
#185000
b10 A
b10 6
17
1<
b10111 ;
b10111 ?
