src/def.v
//Instruction codification

`define LDA   	6'h00
`define LDB   	6'h01
`define LDCA   	6'h02
`define LDCB   	6'h03
`define STA   	6'h04
`define STA   	6'h05

`define ADDA   	6'h06
`define ADDB   	6'h07
`define ADDCA  	6'h08
`define ADDCB  	6'h09
`define SUBA   	6'h0A
`define SUBB   	6'h0B
`define SUBCA  	6'h0C
`define SUBCB  	6'h0D

`define ANDA   	6'h0E
`define ANDB   	6'h0F
`define ANDCA  	6'h10
`define ANDCB  	6'h11
`define ORA   	6'h12
`define ORB   	6'h13
`define ORCA  	6'h14
`define ORCB  	6'h15

`define ASLA   	6'h16
`define ASRA   	6'h17

`define JMP   	6'h18

`define BAEQ   	6'h19
`define BANE   	6'h1A
`define BACS   	6'h1B
`define BACC   	6'h1C
`define BAMI   	6'h1D
`define BAPL   	6'h1E

`define BBEQ   	6'h1F
`define BBNE   	6'h20
`define BBCS   	6'h21
`define BBCC   	6'h22
`define BBMI   	6'h23
`define BBPL   	6'h24

`define NOP   	6'h25

src/decodec.v
//`include "def.v"

module decodec
(
	//Entradas de control
	input wire 		clk,
	input wire		reset,

	//Entradas de datos
	input wire [15:0] 	in,
	input wire [2:0]	flagA,	//{z,c,n}
	input wire [2:0]	flagB,	//{z,c,n}

	//Salidas de control
	output reg [1:0]  	selA,
	output reg [1:0]  	selB,
	output reg  		selM1,
	output reg  		selM2,
	output reg  		wrEnable,
	output reg  		jmpEnable,
	output reg  		branchEnable,

	//Salidas de datos
	output wire [7:0]  	inm,
	output wire [9:0]  	memDir,
	output wire [5:0]  	branchDir,
	output wire [9:0]  	jmpDir,
	output wire [5:0]  	opCode
);

assign inm = {in[7],in[6],in[5],in[4],in[3],in[2],in[1],in[0]};
assign memDir = {in[9],in[8],in[7],in[6],in[5],in[4],in[3],in[2],in[1],in[0]};
assign branchDir = {in[5],in[4],in[3],in[2],in[1],in[0]};
assign jmpDir = {in[9],in[8],in[7],in[6],in[5],in[4],in[3],in[2],in[1],in[0]};
assign opCode = {in[15],in[14],in[13],in[12],in[11],in[10]};

always @ ( posedge clk )
begin
	case (opCode)
	//Oparaciones de transferencia de datos
	`LDA:
	begin
		selA		<= 	2'b11;
		selB		<= 	2'b00;
		selM1		<= 	1'b0;
		selM2		<= 	1'b1;
		wrEnable	<= 	1'b0;
		jmpEnable	 <= 1'b0;
		branchEnable <= 1'b0;			
	end
	`LDB:
	begin
		selA		<= 	2'b00;
		selB		<= 	2'b11;
		selM1		<= 	1'b0;
		selM2		<= 	1'b1;
		wrEnable	<= 	1'b0;
		jmpEnable	 <= 1'b0;
		branchEnable <= 1'b0;			
	end

	`LDCA:
	begin
		selA		<= 	2'b01;
		selB		<= 	2'b00;
		selM1		<= 	1'b1;
		selM2		<= 	1'b0;
		wrEnable	<= 	1'b0;
		jmpEnable	 <= 1'b0;
		branchEnable <= 1'b0;			
	end
	`LDCB:
	begin
		selA		<= 	2'b00;
		selB		<= 	2'b01;
		selM1		<= 	1'b1;
		selM2		<= 	1'b0;
		wrEnable	<= 	1'b0;
		jmpEnable	 <= 1'b0;
		branchEnable <= 1'b0;			
	end

	`STA:
	begin
		selA		<= 	2'b00;
		selB		<= 	2'b00;
		selM1		<= 	1'b0;
		selM2		<= 	1'b0;
		wrEnable	<= 	1'b1;
		jmpEnable	 <= 1'b0;
		branchEnable <= 1'b0;		
	end

	`STB:
	begin
		selA		<= 	2'b00;
		selB		<= 	2'b00;
		selM1		<= 	1'b1;
		selM2		<= 	1'b1;
		wrEnable	<= 	1'b1;
		jmpEnable	 <= 1'b0;
		branchEnable <= 1'b0;		
	end
	//-------------------------------------

	//Oparaciones aritmeticas
	`ADDA:
	begin
		selA		<= 	2'b10;
		selB		<= 	2'b00;
		selM1		<= 	1'b0;
		selM2		<= 	1'b1;
		wrEnable	<= 	1'b0;
		jmpEnable	 <= 1'b0;
		branchEnable <= 1'b0;	
	end
	`ADDB:
	begin
		selA		<= 	2'b00;
		selB		<= 	2'b10;
		selM1		<= 	1'b0;
		selM2		<= 	1'b1;
		wrEnable	<= 	1'b0;
		jmpEnable	 <= 1'b0;
		branchEnable <= 1'b0;
	end

	`ADDCA:
	begin
		selA		<= 	2'b10;
		selB		<= 	2'b00;
		selM1		<= 	1'b0;
		selM2		<= 	1'b0;
		wrEnable	<= 	1'b0;
		jmpEnable	 <= 1'b0;
		branchEnable <= 1'b0;	
	end
	`ADDCB:
	begin
		selA		<= 	2'b00;
		selB		<= 	2'b10;
		selM1		<= 	1'b1;
		selM2		<= 	1'b1;
		wrEnable	<= 	1'b0;
		jmpEnable	 <= 1'b0;
		branchEnable <= 1'b0;
	end

	`SUBA:
	begin
		selA		<= 	2'b10;
		selB		<= 	2'b00;
		selM1		<= 	1'b0;
		selM2		<= 	1'b1;
		wrEnable	<= 	1'b0;
		jmpEnable	 <= 1'b0;
		branchEnable <= 1'b0;	
	end
	`SUBB:
	begin
		selA		<= 	2'b00;
		selB		<= 	2'b10;
		selM1		<= 	1'b0;
		selM2		<= 	1'b1;
		wrEnable	<= 	1'b0;
		jmpEnable	 <= 1'b0;
		branchEnable <= 1'b0;
	end

	`SUBCA:
	begin
		selA		<= 	2'b10;
		selB		<= 	2'b00;
		selM1		<= 	1'b0;
		selM2		<= 	1'b0;
		wrEnable	<= 	1'b0;
		jmpEnable	 <= 1'b0;
		branchEnable <= 1'b0;	
	end
	`SUBCB:
	begin
		selA		<= 	2'b00;
		selB		<= 	2'b10;
		selM1		<= 	1'b1;
		selM2		<= 	1'b1;
		wrEnable	<= 	1'b0;
		jmpEnable	 <= 1'b0;
		branchEnable <= 1'b0;
	end
	//-------------------------------------

	//Oparaciones logicas

	`ANDA:
	begin
		selA		<= 	2'b10;
		selB		<= 	2'b00;
		selM1		<= 	1'b0;
		selM2		<= 	1'b1;
		wrEnable	<= 	1'b0;
		jmpEnable	 <= 1'b0;
		branchEnable <= 1'b0;	
	end
	`ANDB:
	begin
		selA		<= 	2'b00;
		selB		<= 	2'b10;
		selM1		<= 	1'b0;
		selM2		<= 	1'b1;
		wrEnable	<= 	1'b0;
		jmpEnable	 <= 1'b0;
		branchEnable <= 1'b0;
	end

	`ANDCA:
	begin
		selA		<= 	2'b10;
		selB		<= 	2'b00;
		selM1		<= 	1'b0;
		selM2		<= 	1'b0;
		wrEnable	<= 	1'b0;
		jmpEnable	 <= 1'b0;
		branchEnable <= 1'b0;	
	end
	`ANDCB:
	begin
		selA		<= 	2'b00;
		selB		<= 	2'b10;
		selM1		<= 	1'b1;
		selM2		<= 	1'b1;
		wrEnable	<= 	1'b0;
		jmpEnable	 <= 1'b0;
		branchEnable <= 1'b0;
	end

	`ORA:
	begin
		selA		<= 	2'b10;
		selB		<= 	2'b00;
		selM1		<= 	1'b0;
		selM2		<= 	1'b1;
		wrEnable	<= 	1'b0;
		jmpEnable	 <= 1'b0;
		branchEnable <= 1'b0;	
	end
	`ORB:
	begin
		selA		<= 	2'b00;
		selB		<= 	2'b10;
		selM1		<= 	1'b0;
		selM2		<= 	1'b1;
		wrEnable	<= 	1'b0;
		jmpEnable	 <= 1'b0;
		branchEnable <= 1'b0;
	end

	`ORCA:
	begin
		selA		<= 	2'b10;
		selB		<= 	2'b00;
		selM1		<= 	1'b0;
		selM2		<= 	1'b0;
		wrEnable	<= 	1'b0;
		jmpEnable	 <= 1'b0;
		branchEnable <= 1'b0;	
	end
	`ORCB:
	begin
		selA		<= 	2'b00;
		selB		<= 	2'b10;
		selM1		<= 	1'b1;
		selM2		<= 	1'b1;
		wrEnable	<= 	1'b0;
		jmpEnable	 <= 1'b0;
		branchEnable <= 1'b0;
	end

	`ASLA:
	begin
		selA		<= 	2'b00;
		selB		<= 	2'b00;
		selM1		<= 	1'b0;
		selM2		<= 	1'b1;
		wrEnable	<= 	1'b0;
		jmpEnable	 <= 1'b0;
		branchEnable <= 1'b0;	
	end
	`ASRA:
	begin
		selA		<= 	2'b00;
		selB		<= 	2'b00;
		selM1		<= 	1'b0;
		selM2		<= 	1'b1;
		wrEnable	<= 	1'b0;
		jmpEnable	 <= 1'b0;
		branchEnable <= 1'b0;
	end
	//-------------------------------------

	// Operaciones de control de flujo

	`JMP:
	begin
		selA		<= 	2'b00;
		selB		<= 	2'b00;
		selM1		<= 	1'b0;
		selM2		<= 	1'b1;
		wrEnable	<= 	1'b0;
		jmpEnable	 <= 1'b1;
		branchEnable <= 1'b0;
	end
	`BAEQ:
	begin
		if (flagA[2] == 1)
    	begin
      		selA		<= 	2'b00;
			selB		<= 	2'b00;
			selM1		<= 	1'b0;
			selM2		<= 	1'b1;
			wrEnable	<= 	1'b0;
			jmpEnable	 <= 1'b0;
			branchEnable <= 1'b1;	
    	end
  		else
    	begin
      		selA		<= 	2'b00;
			selB		<= 	2'b00;
			selM1		<= 	1'b0;
			selM2		<= 	1'b1;
			wrEnable	<= 	1'b0;
			jmpEnable	 <= 1'b0;
			branchEnable <= 1'b0;	
      	end	
	end
	`BANE:
	begin
		if (flagA[2] == 0)
    	begin
      		selA		<= 	2'b00;
			selB		<= 	2'b00;
			selM1		<= 	1'b0;
			selM2		<= 	1'b1;
			wrEnable	<= 	1'b0;
			jmpEnable	 <= 1'b0;
			branchEnable <= 1'b1;	
    	end
  		else
    	begin
      		selA		<= 	2'b00;
			selB		<= 	2'b00;
			selM1		<= 	1'b0;
			selM2		<= 	1'b1;
			wrEnable	<= 	1'b0;
			jmpEnable	 <= 1'b0;
			branchEnable <= 1'b0;	
      	end	
	end
	`BACS:
	begin
		if (flagA[1] == 1)
    	begin
      		selA		<= 	2'b00;
			selB		<= 	2'b00;
			selM1		<= 	1'b0;
			selM2		<= 	1'b1;
			wrEnable	<= 	1'b0;
			jmpEnable	 <= 1'b0;
			branchEnable <= 1'b1;	
    	end
  		else
    	begin
      		selA		<= 	2'b00;
			selB		<= 	2'b00;
			selM1		<= 	1'b0;
			selM2		<= 	1'b1;
			wrEnable	<= 	1'b0;
			jmpEnable	 <= 1'b0;
			branchEnable <= 1'b0;	
      	end	
	end
	`BACC:
	begin
		if (flagA[1] == 0)
    	begin
      		selA		<= 	2'b00;
			selB		<= 	2'b00;
			selM1		<= 	1'b0;
			selM2		<= 	1'b1;
			wrEnable	<= 	1'b0;
			jmpEnable	 <= 1'b0;
			branchEnable <= 1'b1;	
    	end
  		else
    	begin
      		selA		<= 	2'b00;
			selB		<= 	2'b00;
			selM1		<= 	1'b0;
			selM2		<= 	1'b1;
			wrEnable	<= 	1'b0;
			jmpEnable	 <= 1'b0;
			branchEnable <= 1'b0;	
      	end	
	end
	`BAMI:
	begin
		if (flagA[0] == 1)
    	begin
      		selA		<= 	2'b00;
			selB		<= 	2'b00;
			selM1		<= 	1'b0;
			selM2		<= 	1'b1;
			wrEnable	<= 	1'b0;
			jmpEnable	 <= 1'b0;
			branchEnable <= 1'b1;	
    	end
  		else
    	begin
      		selA		<= 	2'b00;
			selB		<= 	2'b00;
			selM1		<= 	1'b0;
			selM2		<= 	1'b1;
			wrEnable	<= 	1'b0;
			jmpEnable	 <= 1'b0;
			branchEnable <= 1'b0;	
      	end	
	end
	`BAPL:
	begin
		if (flagA[0] == 0)
    	begin
      		selA		<= 	2'b00;
			selB		<= 	2'b00;
			selM1		<= 	1'b0;
			selM2		<= 	1'b1;
			wrEnable	<= 	1'b0;
			jmpEnable	 <= 1'b0;
			branchEnable <= 1'b1;	
    	end
  		else
    	begin
      		selA		<= 	2'b00;
			selB		<= 	2'b00;
			selM1		<= 	1'b0;
			selM2		<= 	1'b1;
			wrEnable	<= 	1'b0;
			jmpEnable	 <= 1'b0;
			branchEnable <= 1'b0;	
      	end	
	end

	//-------------------------------------

	`BBEQ:
	begin
		if (flagB[2] == 1)
    	begin
      		selA		<= 	2'b00;
			selB		<= 	2'b00;
			selM1		<= 	1'b0;
			selM2		<= 	1'b1;
			wrEnable	<= 	1'b0;
			jmpEnable	 <= 1'b0;
			branchEnable <= 1'b1;	
    	end
  		else
    	begin
      		selA		<= 	2'b00;
			selB		<= 	2'b00;
			selM1		<= 	1'b0;
			selM2		<= 	1'b1;
			wrEnable	<= 	1'b0;
			jmpEnable	 <= 1'b0;
			branchEnable <= 1'b0;	
      	end	
	end
	`BBNE:
	begin
		if (flagB[2] == 0)
    	begin
      		selA		<= 	2'b00;
			selB		<= 	2'b00;
			selM1		<= 	1'b0;
			selM2		<= 	1'b1;
			wrEnable	<= 	1'b0;
			jmpEnable	 <= 1'b0;
			branchEnable <= 1'b1;	
    	end
  		else
    	begin
      		selA		<= 	2'b00;
			selB		<= 	2'b00;
			selM1		<= 	1'b0;
			selM2		<= 	1'b1;
			wrEnable	<= 	1'b0;
			jmpEnable	 <= 1'b0;
			branchEnable <= 1'b0;	
      	end	
	end
	`BBCS:
	begin
		if (flagB[1] == 1)
    	begin
      		selA		<= 	2'b00;
			selB		<= 	2'b00;
			selM1		<= 	1'b0;
			selM2		<= 	1'b1;
			wrEnable	<= 	1'b0;
			jmpEnable	 <= 1'b0;
			branchEnable <= 1'b1;	
    	end
  		else
    	begin
      		selA		<= 	2'b00;
			selB		<= 	2'b00;
			selM1		<= 	1'b0;
			selM2		<= 	1'b1;
			wrEnable	<= 	1'b0;
			jmpEnable	 <= 1'b0;
			branchEnable <= 1'b0;	
      	end	
	end
	`BBCC:
	begin
		if (flagB[1] == 0)
    	begin
      		selA		<= 	2'b00;
			selB		<= 	2'b00;
			selM1		<= 	1'b0;
			selM2		<= 	1'b1;
			wrEnable	<= 	1'b0;
			jmpEnable	 <= 1'b0;
			branchEnable <= 1'b1;	
    	end
  		else
    	begin
      		selA		<= 	2'b00;
			selB		<= 	2'b00;
			selM1		<= 	1'b0;
			selM2		<= 	1'b0;
			wrEnable	<= 	1'b0;
			jmpEnable	 <= 1'b0;
			branchEnable <= 1'b0;	
      	end	
	end
	`BBMI:
	begin
		if (flagB[0] == 1)
    	begin
      		selA		<= 	2'b00;
			selB		<= 	2'b00;
			selM1		<= 	1'b0;
			selM2		<= 	1'b1;
			wrEnable	<= 	1'b0;
			jmpEnable	 <= 1'b0;
			branchEnable <= 1'b1;	
    	end
  		else
    	begin
      		selA		<= 	2'b00;
			selB		<= 	2'b00;
			selM1		<= 	1'b0;
			selM2		<= 	1'b1;
			wrEnable	<= 	1'b0;
			jmpEnable	 <= 1'b0;
			branchEnable <= 1'b0;	
      	end	
	end
	`BBPL:
	begin
		if (flagB[0] == 0)
    	begin
      		selA		<= 	2'b00;
			selB		<= 	2'b00;
			selM1		<= 	1'b0;
			selM2		<= 	1'b1;
			wrEnable	<= 	1'b0;
			jmpEnable	 <= 1'b0;
			branchEnable <= 1'b1;	
    	end
  		else
    	begin
      		selA		<= 	2'b00;
			selB		<= 	2'b00;
			selM1		<= 	1'b0;
			selM2		<= 	1'b1;
			wrEnable	<= 	1'b0;
			jmpEnable	 <= 1'b0;
			branchEnable <= 1'b0;	
      	end	
	end
	//-------------------------------------

	//Otras
	`NOP:
	begin
		selA		<= 	2'b00;
		selB		<= 	2'b00;
		selM1		<= 	1'b0;
		selM2		<= 	1'b1;
		wrEnable	<= 	1'b0;
		jmpEnable	 <= 1'b0;
		branchEnable <= 1'b0;			
	end
	//-------------------------------------
	default:
	begin
		selA		<= 	2'b00;
		selB		<= 	2'b00;
		selM1		<= 	1'b0;
		selM2		<= 	1'b1;
		wrEnable	<= 	1'b0;
		jmpEnable	 <= 1'b0;
		branchEnable <= 1'b0;	
	end	
	endcase	
end
endmodule

src/waka.v
`timescale 1ns / 1ps
`include "decodec.v"
`include "def.v"

module waka;

//Inputs

reg [15:0] 	data;
reg [2:0] 	flaga;
reg [2:0] 	flagb;

reg [5:0] 	wOp;

//Outputs
wire [7:0] inm;
wire [9:0] memdir;
wire [5:0] branchdir;
wire [9:0] jmpdir;
wire [5:0] opcode;

wire [1:0]  sela;
wire [1:0]  selb;
wire  		selm1;
wire  		selm2;
wire  		wrenable;
wire  		jmpenable;
wire  		branchenable;


reg Clock;
reg Reset;

always 
begin
	#5 Clock = ! Clock;
end

decodec d0 
(
	.clk(Clock),
	.reset(Reset),

	.selA(sela),
	.selB(selb),
	.selM1(selm1),
	.selM2(selm2),
	.wrEnable(wrenable),
	.jmpEnable(jmpenable),
	.branchEnable(branchenable),

	.inm(inm),
	.memDir(memdir),
	.branchDir(branchdir),
	.jmpDir(jmpdir),
	.opCode(opcode),

	.in(data),
	.flagA(flaga),
	.flagB(flagb)
);


initial 
begin
	Clock = 0;
	#05 	Reset=1; #05 Reset=0;

	#5	data = 16'b000000010000000;	flaga = 3'b000;		flagb = 3'b000;
	#10 data = 16'b000001010000000;	flaga = 3'b000;		flagb = 3'b000;
	#10 data = 16'b000010010000000; flaga = 3'b000;		flagb = 3'b000;	
	#10	data = 16'b000011010000000; flaga = 3'b000;		flagb = 3'b000;
	#10	data = 16'b000100010000000;	flaga = 3'b000;		flagb = 3'b000;
	#10 data = 16'b000101010000000;	flaga = 3'b000;		flagb = 3'b000;
	#10 data = 16'b000110010000000; flaga = 3'b000;		flagb = 3'b000;	
	#10	data = 16'b000111010000000; flaga = 3'b000;		flagb = 3'b000;
	#10	data = 16'b000000010000000;	flaga = 3'b000;		flagb = 3'b000;
	#10 data = 16'b000001010000000;	flaga = 3'b000;		flagb = 3'b000;
	#10 data = 16'b000010010000000; flaga = 3'b000;		flagb = 3'b000;	
	#10	data = 16'b000011010000000; flaga = 3'b000;		flagb = 3'b000;
	#10	data = 16'b000100010000000;	flaga = 3'b000;		flagb = 3'b000;
	#10 data = 16'b000101010000000;	flaga = 3'b000;		flagb = 3'b000;
	#10 data = 16'b000110010000000;	flaga = 3'b000;		flagb = 3'b000;	
	#10	data = 16'b000111010000000;	flaga = 3'b000;		flagb = 3'b000;
	#10 data = 16'b001000010000000;	flaga = 3'b000;		flagb = 3'b000;	
	#10	data = 16'b001001010000000;	flaga = 3'b000;		flagb = 3'b000;
	#10 data = 16'b001010010000000;	flaga = 3'b000;		flagb = 3'b000;	
	#10	data = 16'b001011010000000;	flaga = 3'b000;		flagb = 3'b000;
	#10
	$finish;
end

initial 
begin
	$dumpfile("simDECODEC.vcd");
	$dumpvars;
end


endmodule

src/simDECODEC.vcd
$date
	Tue Jun 30 15:39:56 2015
$end
$version
	Icarus Verilog
$end
$timescale
	1ps
$end
$scope module waka $end
$var wire 6 ! branchdir [5:0] $end
$var wire 1 " branchenable $end
$var wire 8 # inm [7:0] $end
$var wire 10 $ jmpdir [9:0] $end
$var wire 1 % jmpenable $end
$var wire 10 & memdir [9:0] $end
$var wire 6 ' opcode [5:0] $end
$var wire 2 ( sela [1:0] $end
$var wire 2 ) selb [1:0] $end
$var wire 1 * selm1 $end
$var wire 1 + selm2 $end
$var wire 1 , wrenable $end
$var reg 1 - Clock $end
$var reg 1 . Reset $end
$var reg 16 / data [15:0] $end
$var reg 3 0 flaga [2:0] $end
$var reg 3 1 flagb [2:0] $end
$scope module d0 $end
$var wire 6 2 branchDir [5:0] $end
$var wire 1 3 clk $end
$var wire 3 4 flagA [2:0] $end
$var wire 3 5 flagB [2:0] $end
$var wire 16 6 in [15:0] $end
$var wire 8 7 inm [7:0] $end
$var wire 10 8 jmpDir [9:0] $end
$var wire 10 9 memDir [9:0] $end
$var wire 6 : opCode [5:0] $end
$var wire 1 ; reset $end
$var reg 1 < branchEnable $end
$var reg 1 = jmpEnable $end
$var reg 2 > selA [1:0] $end
$var reg 2 ? selB [1:0] $end
$var reg 1 @ selM1 $end
$var reg 1 A selM2 $end
$var reg 1 B wrEnable $end
$upscope $end
$upscope $end
$enddefinitions $end
#0
$dumpvars
xB
xA
x@
bx ?
bx >
x=
x<
x;
bx :
bx 9
bx 8
bx 7
bx 6
bx 5
bx 4
03
bx 2
bx 1
bx 0
bx /
x.
0-
x,
x+
x*
bx )
bx (
bx '
bx &
x%
bx $
bx #
x"
bx !
$end
#5000
0<
0"
0=
0%
0B
0,
1A
1+
0@
0*
b0 ?
b0 )
b0 >
b0 (
1.
1;
1-
13
#10000
0.
0;
0-
03
#15000
b10000000 #
b10000000 7
b10000000 &
b10000000 9
b0 !
b0 2
b10000000 $
b10000000 8
b0 '
b0 :
b0 1
b0 5
b0 0
b0 4
b10000000 /
b10000000 6
1-
13
#20000
0-
03
#25000
b11 >
b11 (
b1010000000 &
b1010000000 9
b1010000000 $
b1010000000 8
1-
13
b1010000000 /
b1010000000 6
#30000
0-
03
#35000
b11 ?
b11 )
b0 >
b0 (
b10000000 &
b10000000 9
b10000000 $
b10000000 8
b1 '
b1 :
1-
13
b10010000000 /
b10010000000 6
#40000
0-
03
#45000
b1010000000 &
b1010000000 9
b1010000000 $
b1010000000 8
1-
13
b11010000000 /
b11010000000 6
#50000
0-
03
#55000
0A
0+
1@
1*
b0 ?
b0 )
b1 >
b1 (
b10000000 &
b10000000 9
b10000000 $
b10000000 8
b10 '
b10 :
1-
13
b100010000000 /
b100010000000 6
#60000
0-
03
#65000
b1010000000 &
b1010000000 9
b1010000000 $
b1010000000 8
1-
13
b101010000000 /
b101010000000 6
#70000
0-
03
#75000
b1 ?
b1 )
b0 >
b0 (
b10000000 &
b10000000 9
b10000000 $
b10000000 8
b11 '
b11 :
1-
13
b110010000000 /
b110010000000 6
#80000
0-
03
#85000
b1010000000 &
b1010000000 9
b1010000000 $
b1010000000 8
1-
13
b111010000000 /
b111010000000 6
#90000
0-
03
#95000
1A
1+
0@
0*
b0 ?
b0 )
b11 >
b11 (
b10000000 &
b10000000 9
b10000000 $
b10000000 8
b0 '
b0 :
1-
13
b10000000 /
b10000000 6
#100000
0-
03
#105000
b1010000000 &
b1010000000 9
b1010000000 $
b1010000000 8
1-
13
b1010000000 /
b1010000000 6
#110000
0-
03
#115000
b11 ?
b11 )
b0 >
b0 (
b10000000 &
b10000000 9
b10000000 $
b10000000 8
b1 '
b1 :
1-
13
b10010000000 /
b10010000000 6
#120000
0-
03
#125000
b1010000000 &
b1010000000 9
b1010000000 $
b1010000000 8
1-
13
b11010000000 /
b11010000000 6
#130000
0-
03
#135000
0A
0+
1@
1*
b0 ?
b0 )
b1 >
b1 (
b10000000 &
b10000000 9
b10000000 $
b10000000 8
b10 '
b10 :
1-
13
b100010000000 /
b100010000000 6
#140000
0-
03
#145000
b1010000000 &
b1010000000 9
b1010000000 $
b1010000000 8
1-
13
b101010000000 /
b101010000000 6
#150000
0-
03
#155000
b1 ?
b1 )
b0 >
b0 (
b10000000 &
b10000000 9
b10000000 $
b10000000 8
b11 '
b11 :
1-
13
b110010000000 /
b110010000000 6
#160000
0-
03
#165000
b1010000000 &
b1010000000 9
b1010000000 $
b1010000000 8
1-
13
b111010000000 /
b111010000000 6
#170000
0-
03
#175000
1B
1,
0@
0*
b0 ?
b0 )
b10000000 &
b10000000 9
b10000000 $
b10000000 8
b100 '
b100 :
1-
13
b1000010000000 /
b1000010000000 6
#180000
0-
03
#185000
b1010000000 &
b1010000000 9
b1010000000 $
b1010000000 8
1-
13
b1001010000000 /
b1001010000000 6
#190000
0-
03
#195000
1A
1+
1@
1*
b10000000 &
b10000000 9
b10000000 $
b10000000 8
b101 '
b101 :
1-
13
b1010010000000 /
b1010010000000 6
#200000
0-
03
#205000
b1010000000 &
b1010000000 9
b1010000000 $
b1010000000 8
1-
13
b1011010000000 /
b1011010000000 6
